{
    "edge1": {
        "id": "e1-2",
        "source": "p1",
        "sourceHandle": "left_out",
        "target": "p2",
        "targetHandle": "right_in"
    },
    "edge2": {
        "id": "e1-3",
        "source": "p1",
        "sourceHandle": "bottom_out",
        "target": "p3",
        "targetHandle": "top_in"
    },
    "edge3": {
        "id": "e1-4",
        "source": "p1",
        "sourceHandle": "top_out",
        "target": "p4",
        "targetHandle": "bottom_in"
    },
    "edge4": {
        "id": "e1-5",
        "source": "p1",
        "sourceHandle": "right_out",
        "target": "p5",
        "targetHandle": "left_in"
    },
    "edge5": {
        "id": "e1-6",
        "source": "p1",
        "target": "p6"
    },
    "edge6": {
        "id": "e2-3",
        "source": "p2",
        "target": "p3"
    },
    "edge7": {
        "id": "e3-4",
        "source": "p3",
        "target": "p4"
    },
    "edge8": {
        "id": "ep1-p100",
        "source": "p1",
        "target": "p100"
    }
}